Workbook

Sheet COGS Estimates
A1: Product ID | B1: Product Name | C1: Category | D1: Region | E1: Supplier | F1: Units Forecast | G1: Material Cost / Unit | H1: Direct Labor / Unit | I1: Packaging / Unit | J1: Freight / Unit | K1: Other COGS / Unit | L1: Total COGS / Unit | M1: Total COGS | N1: Target Gross Margin % | O1: Target Selling Price | P1: Data Quality Note
A2: ZH-001 | B2: Aero Lounge Chair | C2: Furniture | D2: North | E2: Northstar Furnishings | F2: 1200 | G2: 92 | H2: 18 | I2: 7 | J2: 9 | K2: 3 | L2: =SUM(G2:K2) | M2: =F2*L2 | N2: 0.42 | O2: =L2/(1-N2)
A3: ZH-002 | B3: Haven 3-Seater Sofa | C3: Furniture | D3: South | E3: UrbanCraft | F3: 800 | G3: 210 | H3: 34 | I3: 15 | J3: 18 | K3: 5 | L3: =SUM(G3:K3) | M3: =F3*L3 | N3: 0.4 | O3: =L3/(1-N3)
A4: ZH-003 | B4: Luma Side Table | C4: Furniture | D4: West | E4: Oakline Works | F4: 1800 | G4: 38 | H4: 9 | I4: 4 | J4: 5 | K4: 2 | L4: =SUM(G4:K4) | M4: =F4*L4 | N4: 0.45 | O4: =L4/(1-N4)
A5: ZH-004 | B5: Nest Storage Cabinet | C5: Storage | D5: East | E5: HomeCore | F5: 950 | G5: 74 | H5: 15 | I5: 6 | J5: 10 | K5: 3 | L5: =SUM(G5:K5) | M5: =F5*L5 | N5: 0.43 | O5: =L5/(1-N5)
A6: ZH-005 | B6: Mira Floor Lamp | C6: Lighting | D6: North | E6: BrightHouse | F6: 2200 | G6: 26 | H6: 7 | I6: 3 | J6: 4 | K6: 1 | L6: =SUM(G6:K6) | M6: =F6*L6 | N6: 0.48 | O6: =L6/(1-N6)
A7: ZH-006 | B7: Arc Pendant Light | C7: Lighting | D7: South | E7: BrightHouse | F7: 1400 | G7: 41 | H7: 8 | I7: 4 | J7: 6 | K7: 2 | L7: =SUM(G7:K7) | M7: =F7*L7 | N7: 0.46 | O7: =L7/(1-N7)
A8: ZH-007 | B8: Terra Dining Table | C8: Furniture | D8: West | F8: 600 | G8: 155 | H8: 28 | I8: 12 | J8: 17 | K8: 4 | L8: =SUM(G8:K8) | M8: =F8*L8 | N8: 0.39 | O8: =L8/(1-N8) | P8: Missing supplier
A9: ZH-008 | B9: Terra Dining Chair | C9: Furniture | D9: East | E9: Oakline Works | F9: 2400 | G9: 52 | H9: 12 | I9: 5 | J9: 7 | K9: 2 | L9: =SUM(G9:K9) | M9: =F9*L9 | N9: 0.41 | O9: =L9/(1-N9)
A10: ZH-009 | B10: Cloud Bedding Set | C10: Textiles | D10: North | E10: SoftNest | F10: 3000 | G10: 29 | H10: 6 | I10: 3 | J10: 4 | K10: 1 | L10: =SUM(G10:K10) | M10: =F10*L10 | N10: 0.5 | O10: =L10/(1-N10)
A11: ZH-010 | B11: Linen Duvet Cover | C11: Textiles | D11: South | E11: SoftNest | F11: 2600 | G11: 24 | H11: 5 | I11: 3 | J11: 4 | K11: 1 | L11: =SUM(G11:K11) | M11: =F11*L11 | N11: 0.51 | O11: =L11/(1-N11)
A12: ZH-011 | B12: Harbor Bookshelf | C12: Storage | D12: West | E12: UrbanCraft | F12: 1100 | G12: 88 | H12: 17 | I12: 7 | J12: 11 | K12: 3 | L12: =SUM(G12:K12) | M12: =F12*L12 | N12: 0.44 | O12: =L12/(1-N12)
A13: ZH-012 | B13: Cove Coffee Table | C13: Furniture | D13: East | E13: UrbanCraft | F13: 1250 | H13: 13 | I13: 5 | J13: 8 | K13: 2 | L13: =SUM(G13:K13) | M13: =F13*L13 | N13: 0.45 | O13: =L13/(1-N13) | P13: Missing material cost / unit
A14: ZH-013 | B14: Zen Area Rug | C14: Textiles | D14: North | E14: WeaveWell | F14: 1700 | G14: 46 | H14: 8 | I14: 5 | J14: 7 | K14: 2 | L14: =SUM(G14:K14) | M14: =F14*L14 | N14: 0.47 | O14: =L14/(1-N14)
A15: ZH-014 | B15: Breeze Accent Chair | C15: Furniture | D15: South | E15: Northstar Furnishings | F15: 1050 | G15: 83 | H15: 16 | I15: 6 | J15: 8 | K15: 3 | L15: =SUM(G15:K15) | M15: =F15*L15 | N15: 0.43 | O15: =L15/(1-N15)
A16: ZH-015 | B16: Glow Desk Lamp | C16: Lighting | D16: West | E16: BrightHouse | F16: 2800 | G16: 19 | H16: 5 | I16: 2 | J16: 3 | K16: 1 | L16: =SUM(G16:K16) | M16: =F16*L16 | N16: 0.49 | O16: =L16/(1-N16)
A17: ZH-016 | B17: Oak Entry Console | C17: Storage | D17: East | E17: Oakline Works | F17: 700 | G17: 97 | H17: 19 | I17: 8 | J17: 12 | K17: 3 | L17: =SUM(G17:K17) | M17: =F17*L17 | N17: 0.42 | O17: =L17/(1-N17)
A18: ZH-017 | B18: Vista Bar Stool | C18: Furniture | D18: North | E18: HomeCore | F18: -350 | G18: 48 | H18: 10 | I18: 5 | J18: 7 | K18: 2 | L18: =SUM(G18:K18) | M18: =F18*L18 | N18: 0.44 | O18: =L18/(1-N18) | P18: Invalid negative units forecast
A19: ZH-018 | B19: Calm Throw Blanket | C19: Textiles | D19: South | E19: SoftNest | F19: 3500 | G19: 17 | H19: 4 | I19: 2 | J19: 3 | K19: 1 | L19: =SUM(G19:K19) | M19: =F19*L19 | N19: 0.52 | O19: =L19/(1-N19)
A20: ZH-019 | B20: Pulse Smart Lamp | C20: Lighting | D20: West | E20: BrightHouse | F20: 1900 | G20: 63 | H20: 11 | I20: 4 | J20: 8 | K20: 2 | L20: =SUM(G20:K20) | M20: =F20*L20 | N20: 0.45 | O20: =L20/(1-N20)
A21: ZH-020 | B21: Luna Wardrobe | C21: Storage | D21: East | E21: HomeCore | F21: 500 | G21: 168 | H21: 29 | I21: 13 | J21: 21 | K21: 5 | L21: =SUM(G21:K21) | M21: =F21*L21 | N21: 0.38 | O21: =L21/(1-N21)
A22: ZH-021 | B22: Ridge TV Unit | C22: Storage | D22: North | E22: HomeCore | F22: 900 | G22: 105 | H22: 20 | I22: 8 | J22: 12 | K22: 3 | L22: =SUM(G22:K22) | M22: =F22*L22 | N22: 1.15 | O22: =L22/(1-N22) | P22: Invalid target gross margin above 100%
A23: ZH-022 | B23: Halo Mirror | C23: Decor | D23: South | E23: WeaveWell | F23: 1500 | G23: 33 | H23: 7 | I23: 4 | J23: 6 | K23: 2 | L23: =SUM(G23:K23) | M23: =F23*L23 | N23: 0.5 | O23: =L23/(1-N23)
A24: ZH-023 | B24: Vale Ottoman | C24: Furniture | D24: West | E24: Northstar Furnishings | F24: 1300 | G24: 57 | H24: 11 | I24: 5 | J24: 7 | K24: 2 | L24: =SUM(G24:K24) | M24: =F24*L24 | N24: 0.46 | O24: =L24/(1-N24)
A25: ZH-024 | B25: Drift Cushion Set | C25: Textiles | D25: Central | E25: SoftNest | F25: 4200 | G25: 11 | H25: 3 | I25: 1 | J25: 2 | K25: 0.5 | L25: =SUM(G25:K25) | M25: =F25*L25 | N25: 0.53 | O25: =L25/(1-N25) | P25: Unexpected region value; standard regions are North, South, East, West

Sheet Analysis Guide
A1: Key column | B1: Purpose | C1: Expected data / validation
A2: Product ID | B2: Unique identifier for each Zava Home product. | C2: Unique; nonblank.
A3: Product Name | B3: Human-readable product name. | C3: Nonblank.
A4: Category | B4: Product grouping used for cost and margin analysis. | C4: Expected categories such as Furniture, Storage, Lighting, Textiles, Decor.
A5: Region | B5: Forecast/operating region. | C5: Expected values: North, South, East, West.
A6: Supplier | B6: Primary supplier associated with the product. | C6: Nonblank.
A7: Units Forecast | B7: Expected units for the planning period. | C7: Positive whole number.
A8: Material Cost / Unit | B8: Direct material cost per unit. | C8: Non-negative currency.
A9: Direct Labor / Unit | B9: Direct labor cost allocated per unit. | C9: Non-negative currency.
A10: Packaging / Unit | B10: Packaging cost per unit. | C10: Non-negative currency.
A11: Freight / Unit | B11: Inbound freight cost per unit. | C11: Non-negative currency.
A12: Other COGS / Unit | B12: Other direct COGS per unit. | C12: Non-negative currency.
... A16: Target Selling Price | B16: Calculated price based on COGS and target margin. | C16: Should equal Total COGS / Unit ÷ (1 − Target Gross Margin %).
A18: Known data-quality issues intentionally included for the lab
A19: Row 8 | B19: Missing supplier | C19: Use Copilot to identify and explain the impact.
A20: Row 13 | B20: Missing material cost / unit | C20: Use Copilot to identify and explain the impact.
A21: Row 18 | B21: Invalid negative units forecast | C21: Use Copilot to identify and explain the impact.
A22: Row 22 | B22: Invalid target gross margin above 100% | C22: Use Copilot to identify and explain the impact.
A23: Row 25 | B23: Unexpected region value; standard regions are North, South, East, West | C23: Use Copilot to identify and explain the impact.

Sheet Leadership Summary
A1: Metric | B1: Value
A2: Products in dataset | B2: =COUNTA('COGS Estimates'!A2:A25)
A3: Forecast units | B3: =SUM('COGS Estimates'!F2:F25)
A4: Total forecast COGS | B4: =SUM('COGS Estimates'!M2:M25)
A5: Average COGS / unit | B5: =AVERAGE('COGS Estimates'!L2:L25)
A6: Average target gross margin | B6: =AVERAGE('COGS Estimates'!N2:N25)
A7: Data-quality issues included | B7: 5

Sheet Category Summary
A1: Category | B1: Products | C1: Forecast Units | D1: Total COGS
A2: Decor | B2: =COUNTIF('COGS Estimates'!C:C,A2) | C2: =SUMIF('COGS Estimates'!C:C,A2,'COGS Estimates'!F:F) | D2: =SUMIF('COGS Estimates'!C:C,A2,'COGS Estimates'!M:M)
A3: Furniture | B3: =COUNTIF('COGS Estimates'!C:C,A3) | C3: =SUMIF('COGS Estimates'!C:C,A3,'COGS Estimates'!F:F) | D3: =SUMIF('COGS Estimates'!C:C,A3,'COGS Estimates'!M:M)
A4: Lighting | B4: =COUNTIF('COGS Estimates'!C:C,A4) | C4: =SUMIF('COGS Estimates'!C:C,A4,'COGS Estimates'!F:F) | D4: =SUMIF('COGS Estimates'!C:C,A4,'COGS Estimates'!M:M)
A5: Storage | B5: =COUNTIF('COGS Estimates'!C:C,A5) | C5: =SUMIF('COGS Estimates'!C:C,A5,'COGS Estimates'!F:F) | D5: =SUMIF('COGS Estimates'!C:C,A5,'COGS Estimates'!M:M)
A6: Textiles | B6: =COUNTIF('COGS Estimates'!C:C,A6) | C6: =SUMIF('COGS Estimates'!C:C,A6,'COGS Estimates'!F:F) | D6: =SUMIF('COGS Estimates'!C:C,A6,'COGS Estimates'!M:M)
